nlp_tools/__init__.py
nlp_tools/classifiers.py
nlp_tools/constants.py
nlp_tools/dump.py
nlp_tools/loaders.py
nlp_tools/preprocessing.py
nlp_tools/representations.py
nlp_tools/utils.py
nlp_tools_py_lib-0.1.1.dist-info/LICENSE
nlp_tools_py_lib-0.1.1.dist-info/WHEEL
nlp_tools_py_lib-0.1.1.dist-info/METADATA
nlp_tools_py_lib-0.1.1.dist-info/RECORD
