Metadata-Version: 2.1
Name: nlp-tools-py-lib
Version: 0.1.1
Summary: simple nlp library
Home-page: https://github.com/thomas-marquis/nlp-tools-py-lib
License: MIT
Author: thomas.marquis.dev
Author-email: thomas.marquis.dev@gmail.com
Requires-Python: >=3.7,<4.0
Classifier: License :: OSI Approved :: MIT License
Classifier: Programming Language :: Python :: 3
Classifier: Programming Language :: Python :: 3.7
Classifier: Programming Language :: Python :: 3.8
Requires-Dist: nltk (>=3.4.5,<4.0.0)
Requires-Dist: numpy (>=1.18.1,<2.0.0)
Requires-Dist: pandas (>=1.0.1,<2.0.0)
Project-URL: Repository, https://github.com/thomas-marquis/nlp-tools-py-lib
